xltree/__init__.py
xltree/library.py
xltree/settings.py
xltree/models/line_by_line_leaf.py
xltree/models/timeout.py
xltree/models/database/__init__.py
xltree/models/database/library.py
xltree/models/database/source_csv_table_analyzer.py
xltree/models/database/table_formatting.py
xltree/models/tree_structure/__init__.py
xltree/models/tree_structure/converter.py
xltree/worksheet_handle/__init__.py
xltree/worksheet_handle/draw_tools.py
xltree/worksheet_handle/style.py
xltree-0.7.0.dist-info/METADATA
xltree-0.7.0.dist-info/WHEEL
xltree-0.7.0.dist-info/licenses/LICENSE
xltree-0.7.0.dist-info/RECORD
