Metadata-Version: 2.3
Name: xltree
Version: 0.7.0
Summary: Render tree structure diagram using border on Excel.
Project-URL: Repository, https://github.com/muzudho/pyxltree.git
Author-email: "Takahashi Satoshi (Handle Name:むずでょ)" <muzudho1@gmail.com>
Maintainer-email: "Takahashi Satoshi (Handle Name:むずでょ)" <muzudho1@gmail.com>
License: MIT License
License-File: LICENSE
Keywords: border,excel,tree structure diagram
Classifier: Programming Language :: Python
Requires-Dist: numpy>=1.26.4
Requires-Dist: openpyxl>=3.1.5
Requires-Dist: pandas>=2.2.2
